pymyq2/__init__.py
pymyq2/__version__.py
pymyq2/account.py
pymyq2/api.py
pymyq2/const.py
pymyq2/device.py
pymyq2/errors.py
pymyq2/garagedoor.py
pymyq2/lamp.py
pymyq2/lock.py
pymyq2/request.py
pymyq2-3.1.7.dist-info/LICENSE
pymyq2-3.1.7.dist-info/METADATA
pymyq2-3.1.7.dist-info/WHEEL
pymyq2-3.1.7.dist-info/top_level.txt
pymyq2-3.1.7.dist-info/RECORD
